downloadpdf/__init__.py
main/__init__.py
main/download.py
main/scrape.py
util/__init__.py
util/cli.py
util/header.py
util/log.py
util/storage.py
util/url.py
downloadpdf-1.0.10.dist-info/LICENSE
downloadpdf-1.0.10.dist-info/METADATA
downloadpdf-1.0.10.dist-info/WHEEL
downloadpdf-1.0.10.dist-info/top_level.txt
downloadpdf-1.0.10.dist-info/RECORD
